pgs-0.1.4.dist-info/entry_points.txt
pgs-0.1.4.dist-info/METADATA
pgs-0.1.4.dist-info/DESCRIPTION.rst
pgs-0.1.4.dist-info/top_level.txt
pgs-0.1.4.dist-info/RECORD
pgs-0.1.4.dist-info/WHEEL
pgs-0.1.4.dist-info/metadata.json
pgs/app.py
pgs/pgs.py
pgs/bottle.py
pgs/__init__.py
