Metadata-Version: 2.0
Name: pgs
Version: 0.1.4
Summary: A bottle webapp for serving static files from a git branch, or from the local filesystem.
Home-page: https://github.com/westurner/pgs
Author: Wes Turner
Author-email: wes@wrd.nu
License: BSD
Keywords: pgs
Platform: UNKNOWN
Classifier: Development Status :: 2 - Pre-Alpha
Classifier: Intended Audience :: Developers
Classifier: License :: OSI Approved :: MIT License
Classifier: Natural Language :: English
Classifier: Programming Language :: Python :: 2
Classifier: Programming Language :: Python :: 2.6
Classifier: Programming Language :: Python :: 2.7
Classifier: Programming Language :: Python :: 3
Classifier: Programming Language :: Python :: 3.3
Classifier: Programming Language :: Python :: 3.4
